libs/__init__.py
libs/voucher-topic/__init__.py
libs/voucher-topic/voucher_topic.py
mobio/__init__.py
mobio/libs/__init__.py
mobio/libs/voucher_topic/__init__.py
mobio/libs/voucher_topic/voucher_topic.py
thongnv_first_package-0.0.2.dist-info/METADATA
thongnv_first_package-0.0.2.dist-info/WHEEL
thongnv_first_package-0.0.2.dist-info/top_level.txt
thongnv_first_package-0.0.2.dist-info/RECORD
