Metadata-Version: 2.1
Name: thongnv-first-package
Version: 0.0.2
Summary: first package by ThongNV
Home-page: UNKNOWN
Author: ThongNV
Author-email: thongnv@mobio.vn
License: UNKNOWN
Platform: UNKNOWN
Classifier: Programming Language :: Python :: 2
Classifier: License :: OSI Approved :: MIT License
Classifier: Operating System :: OS Independent
